LICENSE
README.md
setup.cfg
setup.py
recan/__init__.py
recan/calc_pairwise_distance.py
recan/rolling_window.py
recan/simgen.py
recan.egg-info/PKG-INFO
recan.egg-info/SOURCES.txt
recan.egg-info/dependency_links.txt
recan.egg-info/requires.txt
recan.egg-info/top_level.txt
test/test.py