Metadata-Version: 2.1
Name: recan
Version: 0.1.4
Summary: recan: recombination analysis tool
Home-page: https://github.com/babinyurii/recan
Download-URL: https://github.com/babinyurii/recan/archive/refs/tags/v_0.1.4.tar.gz
Author: Yuriy Babin
Author-email: babin.yurii@gmail.com
License: MIT
Keywords: DNA recombination,bioinformatics,genetic distance
Classifier: Development Status :: 4 - Beta
Classifier: Intended Audience :: Developers
Classifier: Topic :: Software Development :: Build Tools
Classifier: License :: OSI Approved :: MIT License
Classifier: Programming Language :: Python :: 3
Classifier: Programming Language :: Python :: 3.4
Classifier: Programming Language :: Python :: 3.5
Classifier: Programming Language :: Python :: 3.6
License-File: LICENSE
